mesoSPIM/__init__.py
mesoSPIM/mesoSPIM-shortcut.lnk
mesoSPIM/mesoSPIM.bat
mesoSPIM/mesoSPIM_Control.py
mesoSPIM/config/benchtop_config_V20(computer-J90-01).py
mesoSPIM/config/benchtop_config_V20-shutter568enable.py
mesoSPIM/config/demo_config-H45.py
mesoSPIM/config/demo_config-H45_nodarkmode.py
mesoSPIM/config/demo_config.py
mesoSPIM/config/etl_parameters/ETL-parameters.csv
mesoSPIM/gui/WebcamWindow.ui
mesoSPIM/gui/down-blue.png
mesoSPIM/gui/down-green.png
mesoSPIM/gui/down-red.png
mesoSPIM/gui/icon.ico
mesoSPIM/gui/icon.png
mesoSPIM/gui/icon.svg
mesoSPIM/gui/left-blue.png
mesoSPIM/gui/left-green.png
mesoSPIM/gui/left-red.png
mesoSPIM/gui/mesoSPIM_AcquisitionManagerWindow.ui
mesoSPIM/gui/mesoSPIM_CameraWindow.ui
mesoSPIM/gui/mesoSPIM_MainWindow.ui
mesoSPIM/gui/mesoSPIM_Optimizer.ui
mesoSPIM/gui/mesoSPIM_Optimizer_Results.ui
mesoSPIM/gui/right-blue.png
mesoSPIM/gui/right-green.png
mesoSPIM/gui/right-red.png
mesoSPIM/gui/up-blue.png
mesoSPIM/gui/up-green.png
mesoSPIM/gui/up-limit-green.png
mesoSPIM/gui/up-red.png
mesoSPIM/gui/up-right.png
mesoSPIM/log/example.log
mesoSPIM/scripts/asi_test_read_position.py
mesoSPIM/scripts/asi_test_send_command.py
mesoSPIM/scripts/filtersweep.py
mesoSPIM/scripts/init_hand_controller.py
mesoSPIM/scripts/multiparameter_sweep.py
mesoSPIM/scripts/probing_etl_offsets.py
mesoSPIM/scripts/progressbartest.py
mesoSPIM/scripts/shuttertest.py
mesoSPIM/scripts/snap_sequence.py
mesoSPIM/scripts/timing.py
mesoSPIM/scripts/z_motiontest.py
mesoSPIM/src/WebcamWindow.py
mesoSPIM/src/__init__.py
mesoSPIM/src/mesoSPIM_AcquisitionManagerWindow.py
mesoSPIM/src/mesoSPIM_Camera.py
mesoSPIM/src/mesoSPIM_CameraWindow.py
mesoSPIM/src/mesoSPIM_ContrastWindow.py
mesoSPIM/src/mesoSPIM_Core.py
mesoSPIM/src/mesoSPIM_DemoSerial.py
mesoSPIM/src/mesoSPIM_FilterWheel.py
mesoSPIM/src/mesoSPIM_ImageWriter.py
mesoSPIM/src/mesoSPIM_MainWindow.py
mesoSPIM/src/mesoSPIM_Optimizer.py
mesoSPIM/src/mesoSPIM_ScriptWindow.py
mesoSPIM/src/mesoSPIM_Serial.py
mesospim_control-1.8.0.dist-info/LICENSE
mesospim_control-1.8.0.dist-info/METADATA
mesospim_control-1.8.0.dist-info/WHEEL
mesospim_control-1.8.0.dist-info/entry_points.txt
mesospim_control-1.8.0.dist-info/top_level.txt
mesospim_control-1.8.0.dist-info/RECORD
