Metadata-Version: 2.1
Name: mesospim-control
Version: 1.8.0
Summary: mesoSPIM microscope control
Author-email: Nikita Vladimirov <vladimirov@hifo.uzh.ch>, Fabian Voigt <fvoigt@fas.harvard.edu>
License: GPL-3.0-or-later
Project-URL: Homepage, http://mesospim.org
Project-URL: Source code, https://github.com/mesoSPIM/mesoSPIM-control
Requires-Python: >=3.7
License-File: LICENSE
Requires-Dist: numpy (>=1.17.0)
Requires-Dist: scipy (==1.2.1)
Requires-Dist: PyQt5 (==5.13.1)
Requires-Dist: PyQt5-sip (==12.7.0)
Requires-Dist: nidaqmx (==0.5.7)
Requires-Dist: indexed (==1.2.1)
Requires-Dist: pipython (==2.5.1.3)
Requires-Dist: pyserial (==3.4)
Requires-Dist: pyqtgraph (>=0.12.3)
Requires-Dist: pywinusb (==0.4.2)
Requires-Dist: tifffile (==2021.7.2)
Requires-Dist: qdarkstyle (==2.8.1)
Requires-Dist: npy2bdv (==1.0.7)
Requires-Dist: future (==0.18.2)
